dnd_dice/__init__.py
dnd_dice/__main__.py
dnd_dice/cli.py
dnd_dice/dices.py
dnd_dice/dnd_dice.py
dnd_dice-0.1.1rc1.dist-info/AUTHORS.rst
dnd_dice-0.1.1rc1.dist-info/LICENSE
dnd_dice-0.1.1rc1.dist-info/METADATA
dnd_dice-0.1.1rc1.dist-info/WHEEL
dnd_dice-0.1.1rc1.dist-info/entry_points.txt
dnd_dice-0.1.1rc1.dist-info/top_level.txt
dnd_dice-0.1.1rc1.dist-info/RECORD
