Metadata-Version: 2.1
Name: dnd-dice
Version: 0.1.1rc1
Summary: Shell simulating Dungeons and Dragons dice rolls
Home-page: https://github.com/mustafmst/dnd_dice
Author: Pawel Mstowski
Author-email: pawel.mstowski@gmail.com
License: MIT license
Keywords: dnd_dice
Platform: UNKNOWN
Classifier: Development Status :: 2 - Pre-Alpha
Classifier: Intended Audience :: Developers
Classifier: License :: OSI Approved :: MIT License
Classifier: Natural Language :: English
Classifier: Programming Language :: Python :: 3
Classifier: Programming Language :: Python :: 3.5
Classifier: Programming Language :: Python :: 3.6
Classifier: Programming Language :: Python :: 3.7
Classifier: Programming Language :: Python :: 3.8
Requires-Python: >=3.5
